gam_mcp/__init__.py
gam_mcp/client.py
gam_mcp/server.py
gam_mcp/utils.py
gam_mcp/tools/__init__.py
gam_mcp/tools/advertisers.py
gam_mcp/tools/creatives.py
gam_mcp/tools/line_items.py
gam_mcp/tools/orders.py
gam_mcp/tools/reporting.py
gam_mcp/tools/verification.py
google_ad_manager_mcp-0.1.11.dist-info/METADATA
google_ad_manager_mcp-0.1.11.dist-info/WHEEL
google_ad_manager_mcp-0.1.11.dist-info/entry_points.txt
google_ad_manager_mcp-0.1.11.dist-info/licenses/LICENSE
google_ad_manager_mcp-0.1.11.dist-info/RECORD
