Metadata-Version: 2.4
Name: google-ad-manager-mcp
Version: 0.1.11
Summary: Google Ad Manager MCP Server - An MCP server for managing ad campaigns, line items, creatives, and more
Project-URL: Homepage, https://matious.com
Project-URL: Repository, https://github.com/MatiousCorp/google-ad-manager-mcp
Project-URL: Issues, https://github.com/MatiousCorp/google-ad-manager-mcp/issues
Project-URL: Documentation, https://github.com/MatiousCorp/google-ad-manager-mcp#readme
Project-URL: Custom Development, https://matious.com
Author-email: Youssef Boussafa <youssef@matious.com>
Maintainer-email: Youssef Boussafa <youssef@matious.com>
License: MIT
License-File: LICENSE
Keywords: ad-tech,advertising,ai-assistant,claude,gam,google-ad-manager,mcp,model-context-protocol
Classifier: Development Status :: 4 - Beta
Classifier: Intended Audience :: Developers
Classifier: License :: OSI Approved :: MIT License
Classifier: Operating System :: OS Independent
Classifier: Programming Language :: Python :: 3
Classifier: Programming Language :: Python :: 3.10
Classifier: Programming Language :: Python :: 3.11
Classifier: Programming Language :: Python :: 3.12
Classifier: Topic :: Internet :: WWW/HTTP
Classifier: Topic :: Software Development :: Libraries :: Python Modules
Requires-Python: >=3.10
Requires-Dist: fastmcp<3.0.0,>=2.14.0
Requires-Dist: googleads<49.0.0,>=48.0.0
Requires-Dist: httpx<1.0.0,>=0.28.0
Provides-Extra: dev
Requires-Dist: pytest-asyncio>=0.24.0; extra == 'dev'
Requires-Dist: pytest-cov>=4.0.0; extra == 'dev'
Requires-Dist: pytest>=8.0.0; extra == 'dev'
Requires-Dist: ruff>=0.8.0; extra == 'dev'
